clabe/__init__.py
clabe/banks.py
clabe/errors.py
clabe/py.typed
clabe/types.py
clabe/validations.py
clabe/version.py
tests/__init__.py
tests/test_clabe.py
tests/test_types.py
clabe_bp-1.2.4.dist-info/LICENSE
clabe_bp-1.2.4.dist-info/METADATA
clabe_bp-1.2.4.dist-info/WHEEL
clabe_bp-1.2.4.dist-info/top_level.txt
clabe_bp-1.2.4.dist-info/RECORD
