Metadata-Version: 2.1
Name: clabe-bp
Version: 1.2.4
Summary: Validate and generate the control digit of a CLABE in Mexico
Home-page: https://github.com/lucf25/clabe-python
Author: BanPAY
Author-email: dev@banpay.com
License: UNKNOWN
Platform: UNKNOWN
Classifier: Programming Language :: Python :: 3
Classifier: License :: OSI Approved :: MIT License
Classifier: Operating System :: OS Independent
License-File: LICENSE
Requires-Dist: pydantic (<2.0,>=1.4)
